liti/__init__.py
liti/bigquery.py
liti/cli.py
liti/core/__init__.py
liti/core/backend/__init__.py
liti/core/backend/base.py
liti/core/backend/bigquery.py
liti/core/backend/memory.py
liti/core/base.py
liti/core/client/__init__.py
liti/core/client/bigquery.py
liti/core/context.py
liti/core/error.py
liti/core/file.py
liti/core/function.py
liti/core/logger.py
liti/core/model/__init__.py
liti/core/model/v1/__init__.py
liti/core/model/v1/datatype.py
liti/core/model/v1/manifest.py
liti/core/model/v1/operation/__init__.py
liti/core/model/v1/operation/data/__init__.py
liti/core/model/v1/operation/data/base.py
liti/core/model/v1/operation/data/column.py
liti/core/model/v1/operation/data/sql.py
liti/core/model/v1/operation/data/subclasses.py
liti/core/model/v1/operation/data/table.py
liti/core/model/v1/operation/data/view.py
liti/core/model/v1/operation/ops/__init__.py
liti/core/model/v1/operation/ops/base.py
liti/core/model/v1/operation/ops/column.py
liti/core/model/v1/operation/ops/sql.py
liti/core/model/v1/operation/ops/subclasses.py
liti/core/model/v1/operation/ops/table.py
liti/core/model/v1/operation/ops/view.py
liti/core/model/v1/parse.py
liti/core/model/v1/schema.py
liti/core/model/v1/subclasses.py
liti/core/model/v1/template.py
liti/core/observe/__init__.py
liti/core/observe/observer.py
liti/core/reflect.py
liti/core/runner.py
limber_timber-0.4.1.dist-info/LICENSE
limber_timber-0.4.1.dist-info/METADATA
limber_timber-0.4.1.dist-info/WHEEL
limber_timber-0.4.1.dist-info/entry_points.txt
limber_timber-0.4.1.dist-info/RECORD
