Metadata-Version: 2.3
Name: limber-timber
Version: 0.4.1
Summary: It's data based!
License: MIT
Author: Daniel Tashjian
Author-email: thewopple@gmail.com
Requires-Python: >=3.10
Classifier: Development Status :: 4 - Beta
Classifier: Framework :: Pydantic :: 2
Classifier: Framework :: Pytest
Classifier: License :: OSI Approved :: MIT License
Classifier: Operating System :: OS Independent
Classifier: Programming Language :: Python :: 3
Classifier: Programming Language :: Python :: 3.10
Classifier: Programming Language :: Python :: 3.11
Classifier: Programming Language :: Python :: 3.12
Classifier: Programming Language :: Python :: 3.13
Requires-Dist: devtools (>=0.12)
Requires-Dist: google-cloud-bigquery (>=3.34)
Requires-Dist: pydantic (>=2.11.0,<3.0.0)
Requires-Dist: pyyaml (>=6.0.1,<7.0.0)
Project-URL: Documentation, https://Wopple.github.io/limber-timber
Project-URL: Homepage, https://github.com/Wopple/limber-timber
Project-URL: Repository, https://github.com/Wopple/limber-timber
